AUTHORS.rst
CHANGELOG.md
CONTRIBUTING.rst
LICENSE
MANIFEST.in
README.md
setup.py
examples/gatherdata.py
examples/helpers.py
src/__init__.py
src/requirements.txt
src/pndatapush/__init__.py
src/pndatapush/offline.py
src/pndatapush/pushdata.py
src/pndatapush/sensordata.py
src/pndatapush/test.py
src/pndatapush/utils.py
src/pndatapush.egg-info/PKG-INFO
src/pndatapush.egg-info/SOURCES.txt
src/pndatapush.egg-info/dependency_links.txt
src/pndatapush.egg-info/not-zip-safe
src/pndatapush.egg-info/requires.txt
src/pndatapush.egg-info/top_level.txt