Metadata-Version: 1.1
Name: pndatapush
Version: 0.0.3
Summary: Python module to push data to the Pervasive Nation IoT network. It saves data locally until there is internet access.
Home-page: https://github.com/pervasivenation/python-pndatapush
Author: Pervasive Nation Data Push
Author-email: rocheph@tcd.ie
License: BSD
Platform: UNKNOWN
Classifier: Development Status :: 5 - Production/Stable
Classifier: Intended Audience :: Developers
Classifier: License :: OSI Approved :: BSD License
Classifier: Operating System :: Unix
Classifier: Operating System :: POSIX
Classifier: Programming Language :: Python
Classifier: Programming Language :: Python :: 2.7
Classifier: Topic :: Utilities
